mwbot/__init__.py
mwbot/arktool.py
mwbot/arktool_internet.py
mwbot/bot.py
mwbot/error.py
mwbot/prototype.py
mwbot/utils.py
mwbot-1.0.42.dist-info/WHEEL
mwbot-1.0.42.dist-info/METADATA
mwbot-1.0.42.dist-info/RECORD
