Metadata-Version: 2.1
Name: mwbot
Version: 1.0.42
Summary: 个性化封装的Python Mediawiki API库
License: MIT
Keywords: Mediawiki,API,bot,auto
Author-email: 咕咕mur <2221533105@qq.com>
Requires-Python: >=3.9,<4.0
Requires-Dist: Jinja2>=3.1.4
Requires-Dist: httpx>=0.27.0
Requires-Dist: loguru>=0.7.2
Requires-Dist: mwparserfromhell>=0.6.6
Requires-Dist: regex>=2024.5.15
Requires-Dist: ujson>=5.10.0
Requires-Dist: xmltodict>=0.13.0
